[
  {
    "entity": "login-item-origin.placeholder",
    "excluded_locales": [
      "da",
      "et",
      "eu"
    ],
    "file": "browser/browser/aboutLogins.ftl",
    "type": "equal_to",
    "value": "https://www.example.com"
  },
  {
    "checks": [
      "%s"
    ],
    "entity": "add-engine-url",
    "file": "browser/browser/preferences/addEngine.ftl",
    "type": "include"
  },
  {
    "checks": [
      "+1",
      "\u2303\u21e71"
    ],
    "entity": "profiler-popup-start-shortcut",
    "file": "browser/browser/appmenu.ftl",
    "type": "include"
  },
  {
    "checks": [
      "+2",
      "\u2303\u21e72"
    ],
    "entity": "profiler-popup-capture-shortcut",
    "file": "browser/browser/appmenu.ftl",
    "type": "include"
  },
  {
    "checks": [
      "http://example.com",
      "https://example.com"
    ],
    "entity": "experimental-features-cookie-samesite-schemeful-description",
    "excluded_locales": [
      "da",
      "et",
      "eu"
    ],
    "file": "toolkit/toolkit/featuregates/features.ftl",
    "type": "include"
  }
]